LICENSE
MANIFEST.in
README.rst
setup.py
cradmin_legacy/__init__.py
cradmin_legacy/automodelform.py
cradmin_legacy/context_processors.py
cradmin_legacy/cradmin_testhelpers.py
cradmin_legacy/crapp.py
cradmin_legacy/crinstance.py
cradmin_legacy/crispylayouts.py
cradmin_legacy/crmenu.py
cradmin_legacy/crsettings.py
cradmin_legacy/css_icon_map.py
cradmin_legacy/datetimeutils.py
cradmin_legacy/decorators.py
cradmin_legacy/delay_middleware.py
cradmin_legacy/messages_debug_middleware.py
cradmin_legacy/models.py
cradmin_legacy/python2_compatibility.py
cradmin_legacy/registry.py
cradmin_legacy/renderable.py
cradmin_legacy/urlutils.py
cradmin_legacy/version.json
cradmin_legacy.egg-info/PKG-INFO
cradmin_legacy.egg-info/SOURCES.txt
cradmin_legacy.egg-info/dependency_links.txt
cradmin_legacy.egg-info/not-zip-safe
cradmin_legacy.egg-info/requires.txt
cradmin_legacy.egg-info/top_level.txt
cradmin_legacy/acemarkdown/__init__.py
cradmin_legacy/acemarkdown/widgets.py
cradmin_legacy/apps/__init__.py
cradmin_legacy/apps/cradmin_account/__init__.py
cradmin_legacy/apps/cradmin_account/views/__init__.py
cradmin_legacy/apps/cradmin_activate_account/__init__.py
cradmin_legacy/apps/cradmin_activate_account/urls.py
cradmin_legacy/apps/cradmin_activate_account/utils.py
cradmin_legacy/apps/cradmin_activate_account/templates/cradmin_activate_account/activate.django.html
cradmin_legacy/apps/cradmin_activate_account/templates/cradmin_activate_account/email/html_message.django.html
cradmin_legacy/apps/cradmin_activate_account/templates/cradmin_activate_account/email/subject.django.txt
cradmin_legacy/apps/cradmin_activate_account/templates/cradmin_activate_account/messages/activation-link-expired.django.html
cradmin_legacy/apps/cradmin_activate_account/templates/cradmin_activate_account/messages/activation-link-invalid.django.html
cradmin_legacy/apps/cradmin_activate_account/templates/cradmin_activate_account/messages/success.django.html
cradmin_legacy/apps/cradmin_activate_account/tests/__init__.py
cradmin_legacy/apps/cradmin_activate_account/tests/test_activate.py
cradmin_legacy/apps/cradmin_activate_account/tests/test_utils.py
cradmin_legacy/apps/cradmin_activate_account/views/__init__.py
