Metadata-Version: 1.1
Name: cradmin-legacy
Version: 4.1.0
Summary: Legacy 1.x fork of django cradmin.
Home-page: https://github.com/appressoas/cradmin_legacy
Author: Espen Angell Kristiansen, Tor Johansen, Vegard Angell, Magne Westlie
Author-email: post@appresso.no
License: BSD
Platform: UNKNOWN
Classifier: Development Status :: 4 - Beta
Classifier: Environment :: Web Environment
Classifier: Framework :: Django
Classifier: Intended Audience :: Developers
Classifier: License :: OSI Approved
Classifier: Operating System :: OS Independent
Classifier: Programming Language :: Python
